Workbook

Sheet Dashboard
B1: AFRICAN GAMESKIN GROUP (PTY) LTD — MONTHLY MANAGEMENT ACCOUNT
B2: Month: | C2: July 2026
B4: KEY SALES FIGURES | G4: DEBTORS AGING
B5: Turnover (Total) | C5: =INDEX(Data!$B$2:$B$6,MATCH($C$2,Data!$A$2:$A$6,0)) -> 9999139.2 | G5: Age Band | H5: Amount (R)
B6: Turnover - Exports | C6: =INDEX(Data!$C$2:$C$6,MATCH($C$2,Data!$A$2:$A$6,0)) -> 609648.77 | G6: Current | H6: =INDEX(Data!$AG$2:$AG$6,MATCH($C$2,Data!$A$2:$A$6,0)) -> 6314630.2
B7: Turnover Excl. VAT (Invoiced) | C7: =INDEX(Data!$D$2:$D$6,MATCH($C$2,Data!$A$2:$A$6,0)) -> 10608788 | G7: 30 Days | H7: =INDEX(Data!$AH$2:$AH$6,MATCH($C$2,Data!$A$2:$A$6,0)) -> 2175977.6
B8: Leather Sold | C8: =INDEX(Data!$E$2:$E$6,MATCH($C$2,Data!$A$2:$A$6,0)) -> 31220.53 | G8: 60 Days | H8: =INDEX(Data!$AI$2:$AI$6,MATCH($C$2,Data!$A$2:$A$6,0)) -> 554894.18
B9: Average Selling Price (per m²) | C9: =INDEX(Data!$G$2:$G$6,MATCH($C$2,Data!$A$2:$A$6,0)) -> 324.80529 | G9: 90 Days | H9: =INDEX(Data!$AJ$2:$AJ$6,MATCH($C$2,Data!$A$2:$A$6,0)) -> 126006.73
B10: Leather Purchased | C10: =INDEX(Data!$H$2:$H$6,MATCH($C$2,Data!$A$2:$A$6,0)) -> 32522.46 | G10: 120 Days | H10: =INDEX(Data!$AK$2:$AK$6,MATCH($C$2,Data!$A$2:$A$6,0)) -> 352553.37
B11: Average Purchase Price (per m²) | C11: =INDEX(Data!$J$2:$J$6,MATCH($C$2,Data!$A$2:$A$6,0)) -> 252.78922 | G11: Total Debtors | H11: =INDEX(Data!$AL$2:$AL$6,MATCH($C$2,Data!$A$2:$A$6,0)) -> 9524062.2
B13: SALES BREAKDOWN BY BRANCH (m²) | G13: CREDITORS AGING
B14: Branch | C14: =+C2 -> July 2026 | G14: Age Band | H14: Amount (R)
B15: Durban | C15: =INDEX(Data!$K$2:$K$6,MATCH($C$2,Data!$A$2:$A$6,0)) -> 2265.55 | G15: Current | H15: =INDEX(Data!$AM$2:$AM$6,MATCH($C$2,Data!$A$2:$A$6,0)) -> 2805575.3
B16: JHB | C16: =INDEX(Data!$L$2:$L$6,MATCH($C$2,Data!$A$2:$A$6,0)) -> 11718.75 | G16: 30 Days | H16: =INDEX(Data!$AN$2:$AN$6,MATCH($C$2,Data!$A$2:$A$6,0)) -> 0
B17: Cape Town | C17: =INDEX(Data!$M$2:$M$6,MATCH($C$2,Data!$A$2:$A$6,0)) -> 17236.23 | G17: 60 Days | H17: =INDEX(Data!$AO$2:$AO$6,MATCH($C$2,Data!$A$2:$A$6,0)) -> 0
B18: Total m² sold | C18: =INDEX(Data!$N$2:$N$6,MATCH($C$2,Data!$A$2:$A$6,0)) -> 31220.53 | G18: Total Creditors | H18: =INDEX(Data!$AP$2:$AP$6,MATCH($C$2,Data!$A$2:$A$6,0)) -> 2805575.3
B20: INCOME STATEMENT | G20: BALANCE SHEET SNAPSHOT
C21: Month | D21: YTD | G21: Stock | H21: =INDEX(Data!$AQ$2:$AQ$6,MATCH($C$2,Data!$A$2:$A$6,0)) -> 27842441
B22: Turnover | C22: =INDEX(Data!$O$2:$O$6,MATCH($C$2,Data!$A$2:$A$6,0)) -> 10608788 | D22: =INDEX(Data!$X$2:$X$6,MATCH($C$2,Data!$A$2:$A$6,0)) -> 46357783 | G22: Debtors | H22: =INDEX(Data!$AR$2:$AR$6,MATCH($C$2,Data!$A$2:$A$6,0)) -> 9524062.2
B23: Cost of Sales | C23: =INDEX(Data!$P$2:$P$6,MATCH($C$2,Data!$A$2:$A$6,0)) -> 8549200.2 | D23: =INDEX(Data!$Y$2:$Y$6,MATCH($C$2,Data!$A$2:$A$6,0)) -> 40618458 | G23: Bank | H23: =INDEX(Data!$AS$2:$AS$6,MATCH($C$2,Data!$A$2:$A$6,0)) -> 10697196
B24: Gross Profit | C24: =INDEX(Data!$Q$2:$Q$6,MATCH($C$2,Data!$A$2:$A$6,0)) -> 2059587.7 | D24: =INDEX(Data!$Z$2:$Z$6,MATCH($C$2,Data!$A$2:$A$6,0)) -> 5739325.1 | G24: Creditors | H24: =INDEX(Data!$AT$2:$AT$6,MATCH($C$2,Data!$A$2:$A$6,0)) -> -2805575.3
B25: Other Income | C25: =INDEX(Data!$S$2:$S$6,MATCH($C$2,Data!$A$2:$A$6,0)) -> 312095.86 | D25: =INDEX(Data!$AB$2:$AB$6,MATCH($C$2,Data!$A$2:$A$6,0)) -> 1587782.4 | G25: Total Current Assets | H25: =INDEX(Data!$AU$2:$AU$6,MATCH($C$2,Data!$A$2:$A$6,0)) -> 45258124
B26: Expenses | C26: =INDEX(Data!$T$2:$T$6,MATCH($C$2,Data!$A$2:$A$6,0)) -> 1251113 | D26: =INDEX(Data!$AC$2:$AC$6,MATCH($C$2,Data!$A$2:$A$6,0)) -> 5033048.1
B27: Net Profit | C27: =INDEX(Data!$V$2:$V$6,MATCH($C$2,Data!$A$2:$A$6,0)) -> 1120570.6 | D27: =INDEX(Data!$AE$2:$AE$6,MATCH($C$2,Data!$A$2:$A$6,0)) -> 2294059.5 | G27: STOCK BY BRANCH
G28: Branch | H28: m² | I28: Value (R)
B29: TOP 10 CUSTOMERS | G29: Cape Town | H29: =INDEX(Data!$BA$2:$BA$6,MATCH($C$2,Data!$A$2:$A$6,0)) -> 74815 | I29: =INDEX(Data!$BB$2:$BB$6,MATCH($C$2,Data!$A$2:$A$6,0)) -> 20452395
B30: Customer | C30: m² | D30: Value (R) | G30: JHB | H30: =INDEX(Data!$BC$2:$BC$6,MATCH($C$2,Data!$A$2:$A$6,0)) -> 27800 | I30: =INDEX(Data!$BD$2:$BD$6,MATCH($C$2,Data!$A$2:$A$6,0)) -> 6446325
B31: =INDEX(Data!$BG$2:$BG$6,MATCH($C$2,Data!$A$2:$A$6,0)) -> INS011 - INSPIRE RENTALS PTY LTD | C31: =INDEX(Data!$BH$2:$BH$6,MATCH($C$2,Data!$A$2:$A$6,0)) -> 2208.39 | D31: =INDEX(Data!$BI$2:$BI$6,MATCH($C$2,Data!$A$2:$A$6,0)) -> 559116.25 | G31: Durban | H31: =INDEX(Data!$BE$2:$BE$6,MATCH($C$2,Data!$A$2:$A$6,0)) -> 3769 | I31: =INDEX(Data!$BF$2:$BF$6,MATCH($C$2,Data!$A$2:$A$6,0)) -> 943721
B32: =INDEX(Data!$BJ$2:$BJ$6,MATCH($C$2,Data!$A$2:$A$6,0)) -> JUL003 - JULIANA DESIGNS (PTY) LTD | C32: =INDEX(Data!$BK$2:$BK$6,MATCH($C$2,Data!$A$2:$A$6,0)) -> 1475.87 | D32: =INDEX(Data!$BL$2:$BL$6,MATCH($C$2,Data!$A$2:$A$6,0)) -> 392642.3 | G32: Total Stock | I32: =INDEX(Data!$AZ$2:$AZ$6,MATCH($C$2,Data!$A$2:$A$6,0)) -> 27842441
B33: =INDEX(Data!$BM$2:$BM$6,MATCH($C$2,Data!$A$2:$A$6,0)) -> ROW002 - ROWDY INTERNATIONAL (Pty) Ltd | C33: =INDEX(Data!$BN$2:$BN$6,MATCH($C$2,Data!$A$2:$A$6,0)) -> 1217.25 | D33: =INDEX(Data!$BO$2:$BO$6,MATCH($C$2,Data!$A$2:$A$6,0)) -> 371512.05
B34: =INDEX(Data!$BP$2:$BP$6,MATCH($C$2,Data!$A$2:$A$6,0)) -> INY011 - INYATHI LOUNGE (PTY) LTD | C34: =INDEX(Data!$BQ$2:$BQ$6,MATCH($C$2,Data!$A$2:$A$6,0)) -> 910.15 | D34: =INDEX(Data!$BR$2:$BR$6,MATCH($C$2,Data!$A$2:$A$6,0)) -> 221123.55
B35: =INDEX(Data!$BS$2:$BS$6,MATCH($C$2,Data!$A$2:$A$6,0)) -> LEA04 - LEATHER DIRECT (Pty) Ltd | C35: =INDEX(Data!$BT$2:$BT$6,MATCH($C$2,Data!$A$2:$A$6,0)) -> 833.19 | D35: =INDEX(Data!$BU$2:$BU$6,MATCH($C$2,Data!$A$2:$A$6,0)) -> 208890.6
B36: =INDEX(Data!$BV$2:$BV$6,MATCH($C$2,Data!$A$2:$A$6,0)) -> ALW002 - ALWAYS AROUND (PTY) LTD T/A BEESDAM | C36: =INDEX(Data!$BW$2:$BW$6,MATCH($C$2,Data!$A$2:$A$6,0)) -> 823.34 | D36: =INDEX(Data!$BX$2:$BX$6,MATCH($C$2,Data!$A$2:$A$6,0)) -> 243596.6
B37: =INDEX(Data!$BY$2:$BY$6,MATCH($C$2,Data!$A$2:$A$6,0)) -> BOO002 - BOOT & RALLY (PTY) (LTD) | C37: =INDEX(Data!$BZ$2:$BZ$6,MATCH($C$2,Data!$A$2:$A$6,0)) -> 797.37 | D37: =INDEX(Data!$CA$2:$CA$6,MATCH($C$2,Data!$A$2:$A$6,0)) -> 286136.35
B38: =INDEX(Data!$CB$2:$CB$6,MATCH($C$2,Data!$A$2:$A$6,0)) -> PAN001 - PANGA PANGA FURNITURE | C38: =INDEX(Data!$CC$2:$CC$6,MATCH($C$2,Data!$A$2:$A$6,0)) -> 644.24 | D38: =INDEX(Data!$CD$2:$CD$6,MATCH($C$2,Data!$A$2:$A$6,0)) -> 144822.55
B39: =INDEX(Data!$CE$2:$CE$6,MATCH($C$2,Data!$A$2:$A$6,0)) -> MWI001 - MWIBA HOLDINGS LIMITED | C39: =INDEX(Data!$CF$2:$CF$6,MATCH($C$2,Data!$A$2:$A$6,0)) -> 640.85 | D39: =INDEX(Data!$CG$2:$CG$6,MATCH($C$2,Data!$A$2:$A$6,0)) -> 236150.85
B40: =INDEX(Data!$CH$2:$CH$6,MATCH($C$2,Data!$A$2:$A$6,0)) -> BUR001 - WH Burgundy Collective (Pty) Ltd | C40: =INDEX(Data!$CI$2:$CI$6,MATCH($C$2,Data!$A$2:$A$6,0)) -> 525.51 | D40: =INDEX(Data!$CJ$2:$CJ$6,MATCH($C$2,Data!$A$2:$A$6,0)) -> 209596.35
B41: Top 10 as % of Total Sales | C41: =INDEX(Data!$AV$2:$AV$6,MATCH($C$2,Data!$A$2:$A$6,0)) -> 0.32274148
B42: Credit Notes | C42: =INDEX(Data!$AX$2:$AX$6,MATCH($C$2,Data!$A$2:$A$6,0)) -> 6% of sales | D42: =INDEX(Data!$AY$2:$AY$6,MATCH($C$2,Data!$A$2:$A$6,0)) -> 634599

Sheet Data
A1: month | B1: turnover | C1: turnover_exports | D1: turnover_excl_vat | E1: leather_sold_m2 | F1: leather_sold_value | G1: avg_selling_price | H1: leather_purchased_m2 | I1: leather_purchased_value | J1: avg_purchase_price | K1: durban_m2 | L1: jhb_m2 | M1: cpt_m2 | N1: total_m2_sold | O1: is_turnover | P1: is_cos | Q1: is_gp | R1: is_gp_pct | S1: is_other_income | T1: is_expenses | U1: is_expenses_pct | V1: is_net_profit | W1: is_net_profit_pct | X1: ytd_turnover | Y1: ytd_cos | Z1: ytd_gp | AA1: ytd_gp_pct | AB1: ytd_other_income | AC1: ytd_expenses | AD1: ytd_expenses_pct | AE1: ytd_net_profit | AF1: ytd_net_profit_pct | AG1: debtors_current | AH1: debtors_30 | AI1: debtors_60 | AJ1: debtors_90 | AK1: debtors_120 | AL1: debtors_total | AM1: creditors_current | AN1: creditors_30 | AO1: creditors_60 | AP1: creditors_total | AQ1: stock | AR1: debtors_snapshot | AS1: bank | AT1: creditors_snapshot | AU1: total_current_assets | AV1: top10_pct_of_sales | AW1: credit_notes_label | AX1: credit_notes_pct | AY1: credit_notes_value | AZ1: total_stock_value | BA1: stock_Cape Town_m2 | BB1: stock_Cape Town_value | BC1: stock_JHB_m2 | BD1: stock_JHB_value | BE1: stock_Durban_m2 | BF1: stock_Durban_value | BG1: cust1_name | BH1: cust1_m2 | BI1: cust1_value | BJ1: cust2_name | BK1: cust2_m2 | BL1: cust2_value | BM1: cust3_name | BN1: cust3_m2 | BO1: cust3_value | BP1: cust4_name | BQ1: cust4_m2 | BR1: cust4_value | BS1: cust5_name | BT1: cust5_m2 | BU1: cust5_value | BV1: cust6_name | BW1: cust6_m2 | BX1: cust6_value | BY1: cust7_name | BZ1: cust7_m2 | CA1: cust7_value | CB1: cust8_name | CC1: cust8_m2 | CD1: cust8_value | CE1: cust9_name | CF1: cust9_m2 | CG1: cust9_value | CH1: cust10_name | CI1: cust10_m2 | CJ1: cust10_value
A2: March 2026 | B2: 8458767.2 | C2: 337667.32 | D2: 8796434.5 | E2: 24919.38 | F2: 8193921.2 | G2: 328.81722 | H2: 28543.16 | I2: 6769998.4 | J2: 237.18462 | K2: 2544.32 | L2: 10150.71 | M2: 12223.94 | N2: 24918.97 | O2: 8796434.5 | P2: 7443520.5 | Q2: 1352914 | R2: 0.15380254 | S2: 803916.31 | T2: 988310.05 | U2: 0.11235348 | V2: 1168520.2 | W2: 0.13284021 | X2: 8796434.5 | Y2: 7443520.5 | Z2: 1352914 | AA2: 0.15380254 | AB2: 803916.31 | AC2: 988310.05 | AD2: 0.11235348 | AE2: 1168520.2 | AF2: 0.13284021 | AG2: 5557631.3 | AH2: 3589590.3 | AI2: 438208.68 | AJ2: 221228.3 | AK2: 365380.25 | AL2: 10172039 | AM2: 1397414.2 | AN2: 0 | AO2: 0 | AP2: 1397414.2 | AQ2: 25627566 | AR2: 10172039 | AS2: 7749290.6 | AT2: -1397414.2 | AU2: 42151482 | AV2: 0.31634254 | AW2: CREDIT NOTES: 119x CREDIT NOTES) | AX2: 8% of sales | AY2: 673563.19 | AZ2: 25627566 | BA2: 77489.4 | BB2: 20196660 | BC2: 19734.4 | BD2: 4657318.4 | BE2: 3071.5 | BF2: 773587.99 | BG2: INS011 - INSPIRE RENTALS PTY LTD | BH2: 1873.16 | BI2: 468704.8 | BJ2: BOO002 - BOOT & RALLY (PTY) (LTD) | BK2: 1296.13 | BL2: 452599.8 | BM2: JUL003 - JULIANA DESIGNS (PTY) LTD | BN2: 1198.22 | BO2: 317528.3 | BP2: AFI001 - AFIKA PROMOTIONS | BQ2: 747.45 | BR2: 313483.95 | BS2: LEA04 - LEATHER DIRECT (Pty) Ltd | BT2: 634.24 | BU2: 159416.4 | BV2: ALW002 - ALWAYS AROUND (PTY) LTD T/A BEESDAM | BW2: 490.61 | BX2: 142532.7 | BY2: KZN001 - KZN FASTNERS (PTY) LTD | BZ2: 477.61 | CA2: 95044.39 | CB2: LEA030 - PARIS MANUFACTURING (PTY) LTD | CC2: 408.13 | CD2: 160883.4 | CE2: GAT003 - GATES 2 AFRICA - MIKE | CF2: 398 | CG2: 87816.8 | CH2: LMA001 - LEATHER MASTER | CI2: 359.51 | CJ2: 104547.7
A3: April 2026 | B3: 7877703.6 | C3: 205941.51 | D3: 8083645.1 | E3: 23573.9 | F3: 7643614.4 | G3: 324.24056 | H3: 25487.88 | I3: 6090483.8 | J3: 238.95607 | K3: 2416 | L3: 7996 | M3: 13162 | N3: 23574 | O3: 8083645.1 | P3: 6732664.7 | Q3: 1350980.3 | R3: 0.16712514 | S3: -26096.81 | T3: 921170.66 | U3: 0.11395486 | V3: 403712.86 | W3: 0.049941933 | X3: 16879490 | Y3: 14211986 | Z3: 2667504 | AA3: 0.15803226 | AB3: 777819.5 | AC3: 1895806.4 | AD3: 0.1123142 | AE3: 1549517 | AF3: 0.091798807 | AG3: 4845365.2 | AH3: 3543134.2 | AI3: 1437599.4 | AJ3: 133280.39 | AK3: 362173.82 | AL3: 10321553 | AM3: 2783687.2 | AN3: -551064.84 | AO3: 0 | AP3: 2232622.3 | AQ3: 25469458 | AR3: 10321553 | AS3: 8716363.2 | AT3: -2232622.3 | AU3: 42274752 | AV3: 0.26883206 | AW3: CREDIT NOTES: 108 x CREDIT NOTES) | AX3: 6% of sales | AY3: 491161.49 | AZ3: 25469458 | BA3: 75839 | BB3: 19329329 | BC3: 18843 | BD3: 4446948 | BE3: 4212.79 | BF3: 1023706.9 | BG3: JUL003 - JULIANA DESIGNS (PTY) LTD | BH3: 992.23 | BI3: 262506.6 | BJ3: ALW002 - ALWAYS AROUND (PTY) LTD T/A BEESDAM | BK3: 967.88 | BL3: 267872.35 | BM3: INS011 - INSPIRE RENTALS PTY LTD | BN3: 798.01 | BO3: 192374.3 | BP3: VER001 - VERMONT LEATHER | BQ3: 662.14 | BR3: 225145.35 | BS3: ROW002 - ROWDY INTERNATIONAL (Pty) Ltd | BT3: 618.59 | BU3: 191141.75 | BV3: FAT004 - FF CLOTHING GROUP CC | BW3: 522.95 | BX3: 200319.1 | BY3: LEA04 - LEATHER DIRECT (Pty) Ltd | BZ3: 462.17 | CA3: 115744.2 | CB3: INY011 - INYATHI LOUNGE (PTY) LTD | CC3: 454.67 | CD3: 118315.95 | CE3: BUR001 - WH Burgundy Collective (Pty) Ltd | CF3: 453.68 | CG3: 190664.55 | CH3: CAP003 - CAPE KNIFE CUTTING CC | CI3: 405.1 | CJ3: 121578.45
A4: May 2026 | B4: 9194406.5 | C4: 134522.42 | D4: 9328928.9 | E4: 26938.21 | F4: 8709915.1 | G4: 323.32939 | H4: 29686.34 | I4: 7174856.5 | J4: 241.68882 | K4: 2702 | L4: 9663 | M4: 14573 | N4: 26938 | O4: 9328928.9 | P4: 7958547.2 | Q4: 1370381.7 | R4: 0.14689593 | S4: 280166.36 | T4: 953750.41 | U4: 0.10223579 | V4: 696797.61 | W4: 0.074692134 | X4: 26210086 | Y4: 22855533 | Z4: 3354553.2 | AA4: 0.12798711 | AB4: 878329.36 | AC4: 2860231.9 | AD4: 0.10912715 | AE4: 1372650.6 | AF4: 0.052371084 | AG4: 5628561.9 | AH4: 2778610.7 | AI4: 1093086.8 | AJ4: 276517.89 | AK4: 200499.67 | AL4: 9977276.9 | AM4: 2599600 | AN4: 0 | AO4: 0 | AP4: 2599600 | AQ4: 26440667 | AR4: 9977276.9 | AS4: 9221404.6 | AT4: -2599600 | AU4: 43039749 | AV4: 0.34438331 | AW4: CREDIT NOTES: 93 x CREDIT NOTES | AX4: 5% of sales | AY4: 482483 | AZ4: 26440667 | BA4: 78247 | BB4: 20527322 | BC4: 16859 | BD4: 3704287 | BE4: 4205 | BF4: 999564.09 | BG4: INS011 - INSPIRE RENTALS PTY LTD | BH4: 2096.73 | BI4: 507783.65 | BJ4: JUL003 - JULIANA DESIGNS (PTY) LTD | BK4: 1132.23 | BL4: 300040.95 | BM4: ALW002 - ALWAYS AROUND (PTY) LTD T/A BEESDAM | BN4: 1078.98 | BO4: 308631.8 | BP4: BOO002 - BOOT & RALLY (PTY) (LTD) | BQ4: 967.14 | BR4: 336584.75 | BS4: LEA04 - LEATHER DIRECT (Pty) Ltd | BT4: 816.29 | BU4: 207347.1 | BV4: GAT003 - GATES 2 AFRICA - MIKE | BW4: 787.87 | BX4: 183644.35 | BY4: INY011 - INYATHI LOUNGE (PTY) LTD | BZ4: 683.91 | CA4: 174273.1 | CB4: ROW002 - ROWDY INTERNATIONAL (Pty) Ltd | CC4: 629.04 | CD4: 190119.2 | CE4: JAL001 - JALAD AFRICA PTY LTD | CF4: 574.4 | CG4: 211188.95 | CH4: FAT004 - FF CLOTHING GROUP CC | CI4: 510.48 | CJ4: 211266.6
A5: June 2026 | B5: 8846029.9 | C5: 759904.9 | D5: 9605934.8 | E5: 28111.71 | F5: 9157383.6 | G5: 325.74979 | H5: 34761.64 | I5: 8319792 | J5: 239.3383 | K5: 2362 | L5: 9987 | M5: 15762 | N5: 28111 | O5: 9592256.5 | P5: 9049304 | Q5: 542952.45 | R5: 0.056603204 | S5: 397357.21 | T5: 952854.61 | U5: 0.099335814 | V5: -12544.95 | W5: -0.0013078205 | X5: 35799258 | Y5: 32069257 | Z5: 3730000.5 | AA5: 0.10419212 | AB5: 1275686.6 | AC5: 3831402.2 | AD5: 0.10702463 | AE5: 1174284.9 | AF5: 0.032801934 | AG5: 5750509.5 | AH5: 2659650.2 | AI5: 339704.74 | AJ5: 517460.73 | AK5: 233005.84 | AL5: 9500331 | AM5: 3246489.7 | AN5: 0 | AO5: 0 | AP5: 3246489.7 | AQ5: 28252762 | AR5: 9500331 | AS5: 9644303 | AT5: -3246489.7 | AU5: 44150906 | AV5: 0.3360283 | AW5: CREDIT NOTES: 115 x CREDIT NOTES | AX5: 5% of sales | AY5: 512349.12 | AZ5: 28252762 | BA5: 72417 | BB5: 20103816 | BC5: 26594 | BD5: 6028419 | BE5: 3891.47 | BF5: 999058.3 | BG5: INSPIRE RENTALS PTY LTD | BH5: 1648.56 | BI5: 400521.1 | BJ5: GH LEATHERS LTD | BK5: 1464.08 | BL5: 677878.46 | BM5: JULIANA DESIGNS (PTY) LTD | BN5: 1244.83 | BO5: 329879.95 | BP5: COUCH POTATO | BQ5: 856.94 | BR5: 213084.55 | BS5: INYATHI LOUNGE (PTY) LTD | BT5: 834.04 | BU5: 202000.95 | BV5: ALWAYS AROUND (PTY) LTD T/A BEESDAM | BW5: 787.17 | BX5: 221597.55 | BY5: LEATHER DIRECT (Pty) Ltd | BZ5: 722.42 | CA5: 181422 | CB5: ROWDY INTERNATIONAL (Pty) Ltd | CC5: 707.48 | CD5: 215960.95 | CE5: LEATHER DIRECT (Pty) Ltd | CF5: 597.6 | CG5: 148022.8 | CH5: FF CLOTHING GROUP CC | CI5: 583.21 | CJ5: 232642.6
A6: July 2026 | B6: 9999139.2 | C6: 609648.77 | D6: 10608788 | E6: 31220.53 | F6: 10140593 | G6: 324.80529 | H6: 32522.46 | I6: 8221327.4 | J6: 252.78922 | K6: 2265.55 | L6: 11718.75 | M6: 17236.23 | N6: 31220.53 | O6: 10608788 | P6: 8549200.2 | Q6: 2059587.7 | R6: 0.19413978 | S6: 312095.86 | T6: 1251113 | U6: 0.11793176 | V6: 1120570.6 | W6: 0.10562663 | X6: 46357783 | Y6: 40618458 | Z6: 5739325.1 | AA6: 0.123805 | AB6: 1587782.4 | AC6: 5033048.1 | AD6: 0.10856965 | AE6: 2294059.5 | AF6: 0.049485962 | AG6: 6314630.2 | AH6: 2175977.6 | AI6: 554894.18 | AJ6: 126006.73 | AK6: 352553.37 | AL6: 9524062.2 | AM6: 2805575.3 | AN6: 0 | AO6: 0 | AP6: 2805575.3 | AQ6: 27842441 | AR6: 9524062.2 | AS6: 10697196 | AT6: -2805575.3 | AU6: 45258124 | AV6: 0.32274148 | AW6: CREDIT NOTES: 112 x CREDIT NOTES | AX6: 6% of sales | AY6: 634599 | AZ6: 27842441 | BA6: 74815 | BB6: 20452395 | BC6: 27800 | BD6: 6446325 | BE6: 3769 | BF6: 943721 | BG6: INS011 - INSPIRE RENTALS PTY LTD | BH6: 2208.39 | BI6: 559116.25 | BJ6: JUL003 - JULIANA DESIGNS (PTY) LTD | BK6: 1475.87 | BL6: 392642.3 | BM6: ROW002 - ROWDY INTERNATIONAL (Pty) Ltd | BN6: 1217.25 | BO6: 371512.05 | BP6: INY011 - INYATHI LOUNGE (PTY) LTD | BQ6: 910.15 | BR6: 221123.55 | BS6: LEA04 - LEATHER DIRECT (Pty) Ltd | BT6: 833.19 | BU6: 208890.6 | BV6: ALW002 - ALWAYS AROUND (PTY) LTD T/A BEESDAM | BW6: 823.34 | BX6: 243596.6 | BY6: BOO002 - BOOT & RALLY (PTY) (LTD) | BZ6: 797.37 | CA6: 286136.35 | CB6: PAN001 - PANGA PANGA FURNITURE | CC6: 644.24 | CD6: 144822.55 | CE6: MWI001 - MWIBA HOLDINGS LIMITED | CF6: 640.85 | CG6: 236150.85 | CH6: BUR001 - WH Burgundy Collective (Pty) Ltd | CI6: 525.51 | CJ6: 209596.35
